{
    "bangumi": [
        {
            "asset": {
                "cover": "http://static.acgdb.com/i/28f964071f1985362205e611cb887a541e6a3e8d/w220"
            },
            "intro": {
                "zh_CN": "动画《女高网球部》是根据由Roots（ルーツ）原作、Piyo作画的同名漫画改编的动画作品。"
            },
            "link": {
                "watch": {
                    "zh_CN": "http://acgdb.com/557dd0c81d41c849eba68bff/videos#c=episode"
                }
            },
            "rating": 11,
            "release": "2015-07-06T16:05:00Z",
            "state": 1,
            "tags": {
                "zh_CN": [
                    "续作",
                    "改编",
                    "欢乐",
                    "泡面番",
                    "喜剧",
                    "校园"
                ]
            },
            "title": {
                "en_GB": "Teekyuu 5",
                "ja_JP": "てーきゅう 第5期",
                "zh_CN": "网球并不可笑嘛 (第5季)"
            }
        },
        {
            "asset": {
                "cover": "http://static.acgdb.com/i/ca40abadb29710594ed1e2179e901d7680213eb4/w220"
            },
            "intro": {
                "zh_CN": "気になっていた女の子、白神葉子に告白するため主人公・黒峰朝陽が開けた放課後の教室の扉。するとそこには「牙」と「コウモリのような羽」をはやした葉子の姿があった。白神葉子はなんと吸血鬼だったのだ！ 葉子は他人に吸血鬼であることがばれてしまったら、退学するという約束を父親としていた。それを聞いた朝陽は、「秘密は絶対にばらさない」と葉子に誓う。このことをきっかけに距離が縮まる朝陽と葉子。朝陽はなんとか己の好意を伝えようとするが、次から次にトラブル発生、さらには沢山の『人外の者たち』も現れて…果たして朝陽の恋の行方は…！"
            },
            "link": {
                "watch": {
                    "zh_CN": "http://acgdb.com/557de31e1d41c849eba71a5c/videos#c=episode"
                }
            },
            "rating": 64,
            "release": "2015-07-06T16:35:00Z",
            "state": 1,
            "tags": {
                "zh_CN": [
                    "改编",
                    "欢乐",
                    "日常"
                ]
            },
            "title": {
                "en_GB": "Jitsu wa Watashi wa",
                "ja_JP": "実は私は",
                "zh_CN": "其实我是…"
            }
        },
        {
            "asset": {
                "cover": "http://static.acgdb.com/i/f83301cfd07246dd116f467cf247f3d7bc375963/w220"
            },
            "intro": {
                "zh_CN": "周一出版的JU*P杂志要周三才可以买到，最近的租借店也在10站地意外。蔬菜摆地摊贩卖，从没见过家里上锁。虽然是这样的田园生活，但旭丘分校的女生们却愉快无比。来自个性女孩子们的悠闲日常故事开幕！"
            },
            "link": {
                "watch": {
                    "zh_CN": "http://acgdb.com/Non_Non_Biyori_s2/videos#c=episode"
                }
            },
            "rating": 100,
            "release": "2015-07-06T17:05:00Z",
            "state": 1,
            "tags": {
                "zh_CN": [
                    "续作",
                    "改编",
                    "欢乐",
                    "萌",
                    "日常",
                    "喜剧",
                    "百合",
                    "校园"
                ]
            },
            "title": {
                "en_GB": "Non Non Biyori Repeat",
                "ja_JP": "のんのんびより りぴーと",
                "zh_CN": "悠哉日常大王 Repeat"
            }
        },
        {
            "asset": {
                "cover": "http://static.acgdb.com/i/ac98275d80a047679e6d605a843e775174caa73a/w220"
            },
            "intro": {
                "zh_CN": "一ノ瀬双葉は、デビューしたての新人声優。けれど今のところ、特に際立った個性もなく、残念ながら仕事もほとんどない。アルバイトで生計を立てながら、試行錯誤の日々を送っていた。そんなある日、双葉は、TVアニメ『仏戦士ボサツオン』のアフレコスタジオで、自分と同じ新人声優、萌咲いちごと小花鈴と出会い――。現役声優である私、浅野真澄が、今までの経験と膨大な取材をもとに、好きなことを仕事にしようと格闘する女の子たちの日常を、楽しく、生々しく書きました。声優になりたいあなた、声優・アニメファンのあなた、進路に悩むあなたにこそ見てほしい。誇張もディフォルメもないリアルな私たちの姿、きっと楽しんでもらえるはずです。"
            },
            "link": {
                "watch": {
                    "zh_CN": "http://acgdb.com/557e07e51d41c849eba79450/videos#c=episode"
                }
            },
            "rating": 82,
            "release": "2015-07-07T00:00:00Z",
            "state": 1,
            "tags": {
                "zh_CN": [
                    "改编",
                    "日常"
                ]
            },
            "title": {
                "en_GB": "Sore ga Seiyū!",
                "ja_JP": "それが声優！",
                "zh_CN": "那就是声优！"
            }
        },
        {
            "asset": {
                "cover": "http://static.acgdb.com/i/6c72c6156b58e6cfc8b16629f4f9a2002d7d0823/w220"
            },
            "intro": {
                "zh_CN": "丸山くがね同名轻小说《OVERLORD》改编动画。14年8月在小说第七卷书腰声明动画化。"
            },
            "link": {
                "watch": {
                    "zh_CN": "http://acgdb.com/53fff7f51d41c82e8ba0e798/videos#c=episode"
                }
            },
            "rating": 71,
            "release": "2015-07-07T00:00:00Z",
            "state": 1,
            "tags": {
                "zh_CN": [
                    "改编",
                    "欢乐",
                    "励志",
                    "奇幻",
                    "冒险",
                    "游戏世界观",
                    "穿越"
                ]
            },
            "title": {
                "en_GB": "Over Lord",
                "ja_JP": "OVERLORD",
                "zh_CN": "OVERLORD"
            }
        },
        {
            "asset": {
                "cover": "http://static.acgdb.com/i/60d848c4ef492d02f1d536421b4dc889ccd12850/w220"
            },
            "intro": {
            },
            "link": {
                "watch": {
                    "zh_CN": "http://acgdb.com/557dd8df1d41c808a1933eca/videos#c=episode"
                }
            },
            "rating": 66,
            "release": "2015-07-07T00:00:00Z",
            "state": 1,
            "tags": {
                "zh_CN": [
                    "改编",
                    "欢乐",
                    "卖肉",
                    "喜剧"
                ]
            },
            "title": {
                "en_GB": "Monster Musume",
                "ja_JP": "モンスター娘のいる日常",
                "zh_CN": "魔物娘的同居日常"
            }
        },
        {
            "asset": {
                "cover": "http://static.acgdb.com/i/a254197ed8e2859a9bbed3ce13be5757e2d8115c/w220"
            },
            "intro": {
                "zh_CN": "12人の個性あふれる“枕男子”が毎週登場し、それぞれの特徴を活かした新たな“添い寝”を演出してくれる。"
            },
            "link": {
                "watch": {
                    "zh_CN": "http://acgdb.com/557e92501d41c808a19559ec/videos#c=episode"
                }
            },
            "rating": 6,
            "release": "2015-07-13T16:16:00Z",
            "state": 1,
            "tags": {
                "zh_CN": [
                    "原创",
                    "耽美"
                ]
            },
            "title": {
                "ja_JP": "枕男子",
                "zh_CN": "枕男子"
            }
        }
    ]
}
