<?xml version="1.0" encoding="UTF-8"?>
<Bangumi version="1.0">
	<item>
		<title>
			<ja_JP>180秒で君の耳を幸せにできるか？</ja_JP>
			<zh_CN>180秒能让你的耳朵幸福吗？</zh_CN>
			<en_GB>180 Byou de Kimi no Mimi wo Shiawase ni Dekiru ka?</en_GB>
		</title>
		<state>1</state>
		<rate>8000</rate>
		<episode>12</episode>
		<release>1634227200</release>
		<image>https://lain.bgm.tv/pic/cover/l/dd/75/334495_3ggaa.jpg</image>
		<url>
			<zh_CN>https://bangumi.tv/subject/334495</zh_CN>
		</url>
		<tag>
			<zh_CN>
				<value>ASMR</value>
				<value>耳骚</value>
			</zh_CN>
		</tag>
		<descrip>
			<zh_CN>　　女子高中生泽家月光终于买到了人头麦，准备踏入ASMR的世界。这一切都是因为知道了逐渐变得疏远的青梅竹马“你”迷上了ASMR。“原来如此……这就是……ASMR吗……” 稍稍有些紧张的对着人头麦说话的月光。小心翼翼的凑到了人头麦的耳边。那一刻，想和月光成为好朋友的秋水也入手了一个人头麦，开始研究起了ASMR。看到月光的人头麦的姐姐阳光和妈妈雨读。想从月光手里夺回哥哥“你”的妹妹奈奈子和加奈子。
　　与ASMR相遇的7人，开始了一段有点刺激的日子。</zh_CN>
		</descrip>
	</item>
	<item>
		<title>
			<ja_JP>プラチナエンド</ja_JP>
			<zh_CN>白金终局</zh_CN>
			<en_GB>Platinum End</en_GB>
		</title>
		<state>1</state>
		<rate>10000</rate>
		<episode>24</episode>
		<release>1633624080</release>
		<image>https://lain.bgm.tv/pic/cover/l/bd/e0/322955_2jv8M.jpg</image>
		<url>
			<zh_CN>https://bangumi.tv/subject/322955</zh_CN>
		</url>
		<tag>
			<zh_CN>
				<value>奇幻</value>
				<value>推理</value>
				<value>神魔</value>
				<value>大逃杀</value>
			</zh_CN>
		</tag>
		<descrip>
			<zh_CN>　　「我给你“生存的希望”。」
　　架桥明日由于事故失去了家人，在被领养的亲戚身边也过着痛苦的日子。
对一切都绝望的少年，在初中毕业的那一天，从楼顶纵身而下。
　　但是，少年在那里遇到了一位天使——！？</zh_CN>
		</descrip>
	</item>
	<item>
		<title>
			<ja_JP>白い砂のアクアトープ</ja_JP>
			<zh_CN>白沙的水族馆</zh_CN>
			<en_GB>Shiroi Suna no Aquatope</en_GB>
		</title>
		<state>1</state>
		<rate>10000</rate>
		<episode>24</episode>
		<release>1625761800</release>
		<image>https://i0.hdslb.com/bfs/bangumi/image/ec52c50afbdb0f78c63661f07414e87bc467d7e5.png</image>
		<url>
			<zh_CN>https://www.bilibili.com/bangumi/media/md28234647/</zh_CN>
		</url>
		<tag>
			<zh_CN>
				<value>励志</value>
				<value>青春</value>
				<value>少女</value>
				<value>海洋生物</value>
			</zh_CN>
		</tag>
		<descrip>
			<zh_CN>　　在水族馆工作的18岁女高中生·海咲野空琉，与在东京失去了自己的所属、因而逃走的前偶像宫泽风花相遇了。空琉和风花将各自的想法埋藏于心、在水族馆中度过了一段时光。
　　但是，在那个重要的地方，闭馆的危机正在迫近。
　　少女们的梦想与现实，孤独与朋友，羁绊与纠结——
　　将会在这个夏天展开闪耀的新篇章。</zh_CN>
		</descrip>
	</item>
	<item>
		<title>
			<ja_JP>王様ランキング</ja_JP>
			<zh_CN>国王排名</zh_CN>
			<en_GB>Ousama Ranking</en_GB>
		</title>
		<state>1</state>
		<rate>10000</rate>
		<episode>25</episode>
		<release>1634232300</release>
		<image>https://i0.hdslb.com/bfs/bangumi/image/3d9ca89d2df4603a99b6a5f54bf6b0501ead39aa.png</image>
		<url>
			<zh_CN>https://www.bilibili.com/bangumi/media/md28235154/</zh_CN>
		</url>
		<tag>
			<zh_CN>
				<value>奇幻</value>
				<value>冒险</value>
				<value>成长</value>
				<value>治愈</value>
			</zh_CN>
		</tag>
		<descrip>
			<zh_CN>　　国家的丰饶程度，拥有的强者数量，以及国王本人是否像勇者一样强大，将这些综合起来进行的排名就是“国王排名”。主人公波吉，是国王排名第7名的伯斯王所统治的王国的第一王子。但波吉生来耳朵就听不见，无力得甚至无法好好地挥剑，不光家臣，就连民众都蔑视他「不是当国王的料」。这样的波吉交到了第一个朋友，卡克。随着与卡克的相遇，以及一点点小小的勇气，波吉的人生开始大规模启动——。 </zh_CN>
		</descrip>
	</item>
	<item>
		<title>
			<ja_JP>キミとフィットボクシング</ja_JP>
			<zh_CN>有氧拳击</zh_CN>
			<en_GB>Kimi to Fit Boxing</en_GB>
		</title>
		<state>1</state>
		<rate>8000</rate>
		<episode>12</episode>
		<release>1633092840</release>
		<image>https://lain.bgm.tv/pic/cover/l/30/40/347792_whP0a.jpg</image>
		<url>
			<zh_CN>https://bangumi.tv/subject/347792</zh_CN>
		</url>
		<tag>
			<zh_CN>
				<value>运动</value>
				<value>健身</value>
				<value>拳击</value>
			</zh_CN>
		</tag>
		<descrip>
			<zh_CN>　　剧情就发生在游戏的另一侧!
　　大受欢迎的任天堂Switch游戏《Fit Boxing》系列，已经成为很多玩家日常生活的一部分，其受欢迎的秘密就是有着个性丰富的教练们。我总是和他们在一起，他们时而温柔地教导我，时而严厉地教导我。当然，这只是在玩游戏的时候。如果游戏结束后他们还存在的话。如果你在不看他们时也能行动的话。这个作品，就发生在画面的另一边，游戏的另一边，教练们可爱的日常记录。</zh_CN>
		</descrip>
	</item>
	<item>
		<title>
			<ja_JP>メガトン級ムサシ</ja_JP>
			<zh_CN>百万吨级武藏</zh_CN>
			<en_GB>Megaton-kyuu Musashi</en_GB>
		</title>
		<state>1</state>
		<rate>8000</rate>
		<episode>12</episode>
		<release>1633093200</release>
		<image>https://lain.bgm.tv/pic/cover/l/00/39/343125_rz4eN.jpg</image>
		<url>
			<zh_CN>https://bangumi.tv/subject/343125</zh_CN>
		</url>
		<tag>
			<zh_CN>
				<value>机甲</value>
				<value>战斗</value>
				<value>外星生物</value>
			</zh_CN>
		</tag>
		<descrip>
			<zh_CN>　　故事以被神秘的外星人德拉克塔毁灭了人类的地球为舞台展开。以前人类为了逃避德拉克塔而躲进避难所依克希亚，被消除了毁灭之日记忆的居民们什么都不知道，过着普普通通的生活。但是居民中也有一部分“被选中的人”，正驾驶着名为罗格的巨大机器人与外星人战斗……</zh_CN>
		</descrip>
	</item>
	<item>
		<title>
			<ja_JP>SELECTION PROJECT</ja_JP>
			<zh_CN>SELECTION PROJECT</zh_CN>
			<en_GB>SELECTION PROJECT</en_GB>
		</title>
		<state>1</state>
		<rate>6000</rate>
		<episode>13</episode>
		<release>1633096800</release>
		<image>https://lain.bgm.tv/pic/cover/l/85/e7/321190_xXA8B.jpg</image>
		<url>
			<zh_CN>https://bangumi.tv/subject/321190</zh_CN>
		</url>
		<tag>
			<zh_CN>
				<value>偶像</value>
				<value>选秀</value>
				<value>轻百合</value>
			</zh_CN>
		</tag>
		<descrip>
			<zh_CN>　　每年夏季举办的以偶像为目标的少女们最盛大的登龙门「SELECTION PROJECT」，那是所有以偶像为目标努力着的少女们所憧憬的舞台。还有，也是传说偶像「天泽灯」诞生的地方。美山铃音也是憧憬那个梦之舞台的其中一人。从小就体弱多病的她，在医院的病床上听了无数遍灯的歌曲。她的歌声带给我很多欢笑和勇气。 能成为某人的支柱，能带给某人欢笑，能带给某人幸福……
　　「我也想成为灯那样的偶像。」
　　中学最后的夏天，铃音为了实现梦想，决定挑战第7回「SELECTION PROJECT」。挑战SELECTION的少女们，都是拥有着不想输给任何人的强烈心情、日积月累、魅力独特出众的人。即便如此，能在数千候选人中脱颖而出的明星也只有寥寥数人。现在，为了实现梦想，少女们激烈且残酷的战斗开始了――。 </zh_CN>
		</descrip>
	</item>
</Bangumi>